{
  "id": 14,
  "robots": [
    {"id": "robodendron", "name": "Robodendron"},
    {"id": "snax", "name": "snäx"}
  ],
  "startingBaskets": ["blue", "magenta"],
  "isTieAllowed": true,
  "hasEnded": false,
  "rounds": [
    {
      "scores": [[], []],
      "fouls": [[], []],
      "baskets": ["blue", "magenta"],
      "hasEnded": false,
      "isConfirmed": false,
      "roundMaxLength": 60000,
      "runs": [{"startTime": 1671284070526, "endTime": null}]
    }
  ],
  "ballPlacement": [
    [0, 0],
    [0.94, 1.21],
    [-0.94, -1.21],
    [0.79, 0.3],
    [-0.79, -0.3],
    [-2.06, 1.27],
    [2.06, -1.27],
    [0.99, 0.69],
    [-0.99, -0.69],
    [-0.54, -1.26],
    [0.54, 1.26]
  ]
}